paxter/__init__.py
paxter/__main__.py
paxter/meta.json
paxter/core/__init__.py
paxter/core/charloc.py
paxter/core/charset.py
paxter/core/data.py
paxter/core/enclosing.py
paxter/core/exceptions.py
paxter/core/lexers.py
paxter/core/parser.py
paxter/pyauthor/__init__.py
paxter/pyauthor/environ.py
paxter/pyauthor/visitor.py
paxter/pyauthor/wrappers.py
paxter/pyauthor/funcs/__init__.py
paxter/pyauthor/funcs/controls.py
paxter/pyauthor/funcs/document.py
paxter/pyauthor/funcs/standards.py
paxter-0.6.11.dist-info/LICENSE
paxter-0.6.11.dist-info/METADATA
paxter-0.6.11.dist-info/WHEEL
paxter-0.6.11.dist-info/entry_points.txt
paxter-0.6.11.dist-info/top_level.txt
paxter-0.6.11.dist-info/RECORD
