Metadata-Version: 2.1
Name: paxter
Version: 0.6.11
Summary: Paxter is a document-first, text pre-processing mini-language toolchain, loosely inspired by @-expressions in Racket
Home-page: https://github.com/abhabongse/paxter
Author: Abhabongse Janthong
Author-email: 6845502+abhabongse@users.noreply.github.com
License: Apache-2.0
Project-URL: Documentation, https://paxter.readthedocs.io/
Project-URL: Changelog, https://github.com/abhabongse/paxter/blob/master/CHANGELOG.md
Project-URL: Issue Tracker, https://github.com/abhabongse/paxter/issues
Platform: UNKNOWN
Classifier: Development Status :: 4 - Beta
Classifier: Intended Audience :: Developers
Classifier: License :: OSI Approved :: Apache Software License
Classifier: Programming Language :: Python
Classifier: Programming Language :: Python :: 3
Classifier: Programming Language :: Python :: 3.7
Classifier: Programming Language :: Python :: 3.8
Classifier: Topic :: Software Development :: Pre-processors
Classifier: Topic :: Text Processing
Classifier: Typing :: Typed
Requires-Python: >=3.7
Provides-Extra: extras
Requires-Dist: click (>=5.0) ; extra == 'extras'
